llmtests/__init__.py
llmtests/test_files/simple_changes_over_time.json
llmtests/test_files/simple_memory.json
llmtests/test_files/simplish_memory.json
llmtests-0.0.16.281.dist-info/METADATA
llmtests-0.0.16.281.dist-info/WHEEL
llmtests-0.0.16.281.dist-info/licenses/LICENCE
llmtests-0.0.16.281.dist-info/RECORD
